anubis/__init__.py
anubis/anubis.py
python3_anubis-1.1.0.dist-info/LICENSE
python3_anubis-1.1.0.dist-info/METADATA
python3_anubis-1.1.0.dist-info/WHEEL
python3_anubis-1.1.0.dist-info/top_level.txt
python3_anubis-1.1.0.dist-info/RECORD
