Metadata-Version: 2.1
Name: python3-anubis
Version: 1.1.0
Summary: Library used to discover and find subdomains of domains
Home-page: https://github.com/nmmapper/python3-anubis
Author: nmmapper
Author-email: inquiry@nmmapper.com
License: UNKNOWN
Project-URL: Documentation, https://github.com/nmmapper/python3-anubis
Project-URL: How it is used, https://github.com/nmmapper/python3-anubis
Project-URL: Homepage, https://www.nmmapper.com/
Project-URL: Source, https://github.com/nmmapper/python3-anubis
Project-URL: Subdomain finder, https://www.nmmapper.com/sys/tools/subdomainfinder/
Project-URL: theHarvester online, https://www.nmmapper.com/sys/theharvester/email-harvester-tool/online/
Platform: UNKNOWN
Classifier: Programming Language :: Python :: 3
Classifier: Operating System :: OS Independent
Requires-Python: >=3.6
License-File: LICENSE
Requires-Dist: dnspython
Requires-Dist: httpx
Requires-Dist: requests
